[
  {
    "networkIdName": "urbalurba.no",
    "username": "getout",
    "lastOrgItemExportDate": "2022-11-08T00:20:33.468Z",
    "lastOrgExportRunDate": "2022-12-01T17:12:30.137Z",
    "exchangeToCsvNetworkMapping": "{\"layout\": \"\", \"mapping\": \"default\", \"authorId\": 1, \"template\": \"\", \"username\": \"terchris\", \"verified\": \"off\", \"package_id\": 1, \"menu_status\": 0, \"ping_status\": \"closed\", \"slots_status\": 0, \"expired_after\": 99, \"gallery_style\": \"\", \"comment_status\": \"closed\", \"maxRecords2Read\": 3, \"user_package_id\": 1, \"author_last_name\": \"Robot\", \"wp_page_template\": \"\", \"author_first_name\": \"Urbalurba\", \"minutesSinceChange\": 1440, \"email_contact_widget\": 0, \"opening_hours_status\": 0}",
    "createdById": null,
    "updatedById": null
  },
  {
    "networkIdName": "smartebyernorge.no",
    "username": "smartebyerborge",
    "lastOrgItemExportDate": "2023-01-03T08:41:09.090Z",
    "lastOrgExportRunDate": "2023-01-03T08:41:19.037Z",
    "exchangeToCsvNetworkMapping": "{\"layout\": \"\", \"mapping\": \"default\", \"authorId\": 1, \"template\": \"\", \"username\": \"terchris\", \"verified\": \"off\", \"package_id\": 1, \"menu_status\": 0, \"ping_status\": \"closed\", \"slots_status\": 0, \"expired_after\": 99, \"gallery_style\": \"\", \"comment_status\": \"closed\", \"maxRecords2Read\": 500, \"user_package_id\": 1, \"author_last_name\": \"Robot\", \"wp_page_template\": \"\", \"author_first_name\": \"Urbalurba\", \"minutesSinceChange\": 1440, \"email_contact_widget\": 0, \"opening_hours_status\": 0}",
    "createdById": null,
    "updatedById": null
  }
]